home/urbi/.local/share/applications/rdplot.desktop
home/urbi/.local/share/icons/PLOT64.png
rdplot/SimulationDataItem.py
rdplot/SimulationDataItem.py~
rdplot/__init__.py
rdplot/__main__.py
rdplot/model.py
rdplot/version.txt
rdplot/view.py
rdplot/SimulationDataItemClasses/CsvLogs.py
rdplot/SimulationDataItemClasses/DatLogs.py
rdplot/SimulationDataItemClasses/DecoderAnalyserLogs.py
rdplot/SimulationDataItemClasses/EncoderLogs.py
rdplot/SimulationDataItemClasses/__init__.py
rdplot/Widgets/MainWindow.py
rdplot/Widgets/PlotWidget.py
rdplot/Widgets/__init__.py
rdplot/docs/about.html
rdplot/lib/BD.py
rdplot/logo/PLOT1024.icns
rdplot/logo/PLOT1024.png
rdplot/logo/PLOT128.png
rdplot/logo/PLOT16.png
rdplot/logo/PLOT256.png
rdplot/logo/PLOT32.png
rdplot/logo/PLOT512.png
rdplot/logo/PLOT64.png
rdplot/logo/about_IENTLogo.png
rdplot/logo/plot512_0wd_icon.ico
rdplot/misc/latex_table_template.tex
rdplot/misc/rdplot.desktop
rdplot/ui/mainWindow.ui
rdplot/ui/plotWidget.ui
rdplot-1.3.4.dist-info/LICENSE.txt
rdplot-1.3.4.dist-info/METADATA
rdplot-1.3.4.dist-info/WHEEL
rdplot-1.3.4.dist-info/entry_points.txt
rdplot-1.3.4.dist-info/top_level.txt
rdplot-1.3.4.dist-info/RECORD
