Metadata-Version: 2.1
Name: rdplot
Version: 1.3.4
Summary: A plot tool for rate distortion curves
Home-page: https://github.com/IENT/RDPlot
Author: Jens Schneider, Johannes Sauer, Christoph Weyer, Alex Schmidt
Author-email: schneider@ient.rwth-aachen.de
License: GPL-v3
Keywords: video-coding bjontegaard-delta rate-distortion-plots
Platform: UNKNOWN
Classifier: Development Status :: 4 - Beta
Classifier: Intended Audience :: Science/Research
Classifier: Topic :: Scientific/Engineering :: Information Analysis
Classifier: License :: OSI Approved :: MIT License
Classifier: Programming Language :: Python :: 3
Classifier: Programming Language :: Python :: 3.7
Classifier: Programming Language :: Python :: 3.8
License-File: LICENSE.txt
Requires-Dist: cycler
Requires-Dist: matplotlib (==3.4.2)
Requires-Dist: numpy
Requires-Dist: py
Requires-Dist: pyparsing
Requires-Dist: pyqt5
Requires-Dist: pytest
Requires-Dist: python-dateutil
Requires-Dist: pytz
Requires-Dist: six
Requires-Dist: scipy
Requires-Dist: tabulate
Requires-Dist: mpldatacursor
Requires-Dist: xmltodict
Requires-Dist: jsonpickle
Requires-Dist: tikzplotlib
Requires-Dist: Pillow
